Metadata-Version: 1.0
Name: sshmux
Version: 0.2.0
Summary: Work on multiple machines over ssh at once
Home-page: https://github.com/dvopsway/sshmux
Author: Padmakar Ojha
Author-email: padmakar.ojha@gmail.com
License: GPL-3.0
Keywords: ssh
Platform: UNKNOWN
